sees/__init__.py
sees/__main__.py
sees/_plane.py
sees/cli.py
sees/config.py
sees/model.py
sees/schema.py
sees/section.py
sees/state.py
sees/tcl.py
sees/views.py
sees/archive/_render.py
sees/canvas/canvas.py
sees/canvas/gltflib.py
sees/canvas/mpl.py
sees/canvas/ply.py
sees/canvas/tri.py
sees/canvas/femgl/__init__.py
sees/canvas/femgl/convert/convert.py
sees/canvas/femgl/convert/example.py
sees/frame/__init__.py
sees/frame/extrude.py
sees/utilities/alpha_shape.py
sees/utilities/consolidate.py
semm-0.0.0.dist-info/METADATA
semm-0.0.0.dist-info/WHEEL
semm-0.0.0.dist-info/entry_points.txt
semm-0.0.0.dist-info/top_level.txt
semm-0.0.0.dist-info/RECORD
